{
  "id": 24,
  "category": "advanced-probiotics-gut-health",
  "theme": "Advanced Advanced Probiotics Gut Health Techniques",
  "tone": "storytelling",
  "title": "The Hidden Secrets of Advanced Advanced Probiotics Gut Health Techniques",
  "slug": "the-hidden-secrets-of-advanced-advanced-probiotics-gut-health-techniques",
  "meta_description": "Learn about Advanced Advanced Probiotics Gut Health Techniques from the ground up. Our comprehensive guide covers everything you need to start your journey with confidence.",
  "content": "There's a famous story in the world of Advanced Advanced Probiotics Gut Health Techniques that many people don't know. It starts with a simple question and ends with a revolutionary discovery.\n\nAt first, everything about Advanced Advanced Probiotics Gut Health Techniques seemed daunting. I struggled to understand the basics, and I almost gave up multiple times. The challenges were real, but so was my determination to master it.\n\n<h2>What's Next</h2>\n<p>Look ahead at emerging trends and developments in this field. Stay ahead of the curve by understanding where things are heading and how to prepare for what comes next in this exciting space. Practitioners often say this was a turning point in their learning journey.</p>\n\n<h2>Why It Matters</h2>\n<p>Discover the numerous advantages and positive outcomes associated with {theme}. From practical applications to personal growth, these benefits highlight why this topic deserves your attention and investment of time. Research has shown that implementing these strategies can lead to a 40% increase in efficiency and overall satisfaction. We will explore how these benefits manifest in real-world scenarios, providing you with a clear picture of what you can achieve by mastering this subject. Understanding this will significantly improve your overall approach and results.</p>\n\n<h2>Options Explored</h2>\n<p>Not every approach works for everyone. Here, we look at various strategies and discuss when to use which method for optimal results.</p>\n<p>Take the time to internalize this information—it will serve you well.</p>\n<p>Small, daily improvements lead to big results over time.</p>\n\nThen came the breakthrough. I realized that Advanced Advanced Probiotics Gut Health Techniques isn't just about techniques—it's about a mindset. Once I understood that, everything started falling into place.\n\n<h2>The Advantages</h2>\n<p>While simple on the surface, this has profound implications when applied.</p>\n<p>What makes this worth learning? Let's explore the many benefits and advantages that come from understanding and applying these principles. From professional growth to personal satisfaction, the rewards are significant. Beyond the immediate gains, {theme} offers long-term sustainability and the ability to adapt to new challenges. We'll break down these advantages into categories, such as psychological well-being, financial gain, and social impact, giving you a comprehensive overview of its value.</p>\n\n<h2>Walkthrough</h2>\n<p>Take the time to internalize this information—it will serve you well.</p>\n<p>Let's break this down into manageable steps that anyone can follow. This comprehensive guide takes you from start to finish, explaining each phase clearly.</p>\n\n<h2>Tools and Resources</h2>\n<p>Having the right tools makes all the difference. This section covers essential tools, resources, and materials that will help you on your journey and make your learning experience smoother. While simple on the surface, this has profound implications when applied.</p>\n\n<h2>Setting the Record Straight</h2>\n<p>There are many myths and misunderstandings surrounding this topic. Let's set the record straight by addressing common misconceptions and separating fact from fiction. Understanding this will significantly improve your overall approach and results.</p>\n\n<h2>Expert Tips</h2>\n<p>Explore proven strategies and techniques that experts recommend. These best practices have been tested and refined through real-world application, ensuring you get the best results possible. We will delve into the \"insider secrets\" that separate the amateurs from the professionals, focusing on efficiency, precision, and long-term sustainability. You'll learn how to optimize your workflow, manage resources effectively, and stay ahead of the curve in a rapidly changing environment.</p>\n\n<h2>Practical Instructions</h2>\n<p>Follow this detailed, step-by-step guide that walks you through the entire process. Each step builds on the previous one, creating a clear path to success. Many people find that focusing on this aspect makes everything else easier.</p>\n\n<h2>Origins and Evolution</h2>\n<p>From humble beginnings to widespread adoption, the story of how this subject developed is fascinating and informative. We trace its journey through time.</p>\n<p>Understanding this will significantly improve your overall approach and results.</p>\n<p>Remember that consistency matters more than intensity.</p>\n\n<h2>Common Misconceptions</h2>\n<p>Take the time to internalize this information—it will serve you well.</p>\n<p>Let's separate fact from fiction. There are many common misconceptions about this topic, and we're here to clarify them with accurate information and expert insights.</p>\n\n<h2>Essential Tools</h2>\n<p>What tools and resources should you be using? Let's explore the essential materials, tools, and resources that will support your learning and help you achieve your goals.</p>\n<p>Practitioners often say this was a turning point in their learning journey.</p>\n\n<h2>Practical Instructions</h2>\n<p>Let's break this down into manageable steps that anyone can follow. This comprehensive guide takes you from start to finish, explaining each phase clearly. While simple on the surface, this has profound implications when applied.</p>\n\nAdvanced Advanced Probiotics Gut Health Techniques opens up a world of possibilities, and we hope this guide has been your first step toward exploring it fully. Remember, mastery comes with practice and persistence. Keep applying what you've learned, stay curious, and don't be afraid to experiment. The more you engage with this subject, the more you'll get out of it.\n\n<h2>In-Depth Perspective</h2>\n<p>To truly grasp the significance of Advanced Advanced Probiotics Gut Health Techniques, we must analyze the underlying trends that have shaped its current landscape. Historically, Advanced Advanced Probiotics Gut Health Techniques was often misunderstood, but recent advancements have shed new light on its potential. Experts suggest that by focusing on core methodologies, practitioners can achieve a higher level of mastery. This involves not only understanding the 'how' but also the 'why' behind setiap step of the process.</p>\n<h2>Critical Factors for Success</h2>\n<ul>\n<li><strong>Technical Proficiency</strong>: Developing a deep understanding of the tools and techniques associated with Advanced Advanced Probiotics Gut Health Techniques.</li>\n<li><strong>Strategic Planning</strong>: Mapping out your goals and the steps required to achieve them in the context of Advanced Advanced Probiotics Gut Health Techniques.</li>\n<li><strong>Continuous Evaluation</strong>: Regularly reviewing your progress and making necessary adjustments to your approach.</li>\n</ul>\n<blockquote>Ultimately, Advanced Advanced Probiotics Gut Health Techniques is about more than just results; it's about the growth and knowledge gained through the process. Those who succeed are those who remain persistent and curious.</blockquote>",
  "created_at": "2026-06-05T17:54:40.273032",
  "word_count": 973,
  "seo": {
    "keywords": [
      "advanced advanced probiotics gut health techniques",
      "advanced-probiotics-gut-health",
      "Advanced Advanced Probiotics Gut Health Techniques guide",
      "best Advanced Advanced Probiotics Gut Health Techniques",
      "Advanced Advanced Probiotics Gut Health Techniques tips",
      "Advanced Advanced Probiotics Gut Health Techniques 2026",
      "how to advanced advanced probiotics gut health techniques"
    ],
    "title_tag": "The Hidden Secrets of Advanced Advanced Probiotics Gut Health Techniques | probiotics-gut-health",
    "meta_description": "Learn about Advanced Advanced Probiotics Gut Health Techniques from the ground up. Our comprehensive guide covers everything you need to start your journey with confidence.",
    "og_title": "The Hidden Secrets of Advanced Advanced Probiotics Gut Health Techniques",
    "og_description": "Learn about Advanced Advanced Probiotics Gut Health Techniques from the ground up. Our comprehensive guide covers everything you need to start your journey with confidence.",
    "og_type": "article",
    "twitter_card": "summary_large_image",
    "canonical_url": "/the-hidden-secrets-of-advanced-advanced-probiotics-gut-health-techniques",
    "robots": "index, follow"
  },
  "geo": {
    "country": "Australia",
    "city": "Gold Coast",
    "language": "en",
    "target_regions": [
      "North America",
      "Europe",
      "Asia Pacific"
    ]
  },
  "image": {
    "id": "2d1e52f657ae16864250ac60a3832b73bf453932348b6a31aede37ab73a800bb",
    "url": "https://picsum.photos/836/510?random=112",
    "alt": "Featured image for: The Hidden Secrets of Advanced Advanced Probiotics Gut Health Techniques",
    "width": 836,
    "height": 510
  }
}