{
  "id": 37,
  "category": "tips-probiotics-gut-health",
  "theme": "Common Mistakes in Probiotics Gut Health Tips",
  "tone": "academic",
  "title": "Common Mistakes in Probiotics Gut Health Tips 101: Complete Beginner's Guide",
  "slug": "common-mistakes-in-probiotics-gut-health-tips-101-complete-beginners-guide",
  "meta_description": "Take your knowledge of Common Mistakes in Probiotics Gut Health Tips to the next level with our detailed guide. Comprehensive coverage of all essential aspects.",
  "content": "Abstract: This paper examines the multi-faceted nature of Common Mistakes in Probiotics Gut Health Tips. Welcome to the ultimate resource on Common Mistakes in Probiotics Gut Health Tips. This article brings together expert insights, practical advice, and proven strategies to help you master this subject. Whether you're just starting or looking to improve, you'll find what you need here.\n\n<h2>Options Explored</h2>\n<p>There are multiple ways to approach this topic, each with its own strengths. This section compares different methodologies to help you choose what works best for you. While simple on the surface, this has profound implications when applied.</p>\n\n<h2>The Roadmap to Success</h2>\n<p>Learn how to begin your journey with practical, actionable steps. This section provides a clear roadmap to help you get started on the right foot and avoid common pitfalls. We recommend starting with a thorough self-assessment to identify your current strengths and areas for improvement. From there, we'll guide you through the process of setting realistic goals and creating a personalized plan that fits your unique schedule and lifestyle. While simple on the surface, this has profound implications when applied.</p>\n\n<h2>Expert Q&A</h2>\n<p>Got questions? We've got answers. This section addresses the most common inquiries and provides valuable perspectives from experienced practitioners.</p>\n<p>Many people find that focusing on this aspect makes everything else easier.</p>\n<p>The more you practice this, the more natural it will become.</p>\n\n<h2>Tools and Resources</h2>\n<p>What tools and resources should you be using? Let's explore the essential materials, tools, and resources that will support your learning and help you achieve your goals.</p>\n<p>Practitioners often say this was a turning point in their learning journey.</p>\n\n<h2>Going Further</h2>\n<p>While simple on the surface, this has profound implications when applied.</p>\n<p>Ready to take things to the next level? This section covers more advanced techniques and approaches for those who want to deepen their expertise and go beyond the basics.</p>\n\n📖 **Real World Application**: One practitioner started with just 15 minutes per day and saw significant improvements within 3 weeks. They credit their success to consistent practice and applying what they learned immediately.\n\n<h2>The Advantages</h2>\n<p>Discover the numerous advantages and positive outcomes associated with {theme}. From practical applications to personal growth, these benefits highlight why this topic deserves your attention and investment of time. Research has shown that implementing these strategies can lead to a 40% increase in efficiency and overall satisfaction. We will explore how these benefits manifest in real-world scenarios, providing you with a clear picture of what you can achieve by mastering this subject.</p>\n<p>Many people find that focusing on this aspect makes everything else easier.</p>\n\n> \"Practice makes perfect.\" - Proverb\n\n<h2>Historical Context</h2>\n<p>From humble beginnings to widespread adoption, the story of how this subject developed is fascinating and informative. We trace its journey through time.</p>\n\n<h2>The Core of Common Mistakes in Probiotics Gut Health Tips</h2>\n<p>Let's start with the basics: what exactly is {theme} all about? We'll explore the core definitions and key concepts that form the foundation of this fascinating topic. Understanding these fundamentals is crucial for everything that follows. We will delve into the underlying mechanics, exploring how different elements interact with each other to create a cohesive whole, and why this particular subject has gained such significant traction in recent times.</p>\n<p>Many people find that focusing on this aspect makes everything else easier.</p>\n\n<h2>Why It Matters</h2>\n<p>What makes this worth learning? Let's explore the many benefits and advantages that come from understanding and applying these principles. From professional growth to personal satisfaction, the rewards are significant. Beyond the immediate gains, {theme} offers long-term sustainability and the ability to adapt to new challenges. We'll break down these advantages into categories, such as psychological well-being, financial gain, and social impact, giving you a comprehensive overview of its value.</p>\n<p>Take the time to internalize this information—it will serve you well.</p>\n\nAs we wrap up this guide on Common Mistakes in Probiotics Gut Health Tips, it's clear that this is a subject with depth and potential. We've covered the essentials, explored key concepts, and provided practical advice that you can start using immediately. Keep learning, keep practicing, and you'll continue to see progress and improvement over time. Thank you for joining us on this journey!\n\n<h2>Expert Analysis</h2>\n<p>To truly grasp the significance of Common Mistakes in Probiotics Gut Health Tips, we must analyze the underlying trends that have shaped its current landscape. Historically, Common Mistakes in Probiotics Gut Health Tips was often misunderstood, but recent advancements have shed new light on its potential. Experts suggest that by focusing on core methodologies, practitioners can achieve a higher level of mastery. This involves not only understanding the 'how' but also the 'why' behind setiap step of the process.</p>\n<h2>Critical Factors for Success</h2>\n<ul>\n<li><strong>Technical Proficiency</strong>: Developing a deep understanding of the tools and techniques associated with Common Mistakes in Probiotics Gut Health Tips.</li>\n<li><strong>Strategic Planning</strong>: Mapping out your goals and the steps required to achieve them in the context of Common Mistakes in Probiotics Gut Health Tips.</li>\n<li><strong>Continuous Evaluation</strong>: Regularly reviewing your progress and making necessary adjustments to your approach.</li>\n</ul>\n<blockquote>Ultimately, Common Mistakes in Probiotics Gut Health Tips is about more than just results; it's about the growth and knowledge gained through the process. Those who succeed are those who remain persistent and curious.</blockquote>",
  "created_at": "2026-06-05T17:54:40.275523",
  "word_count": 878,
  "seo": {
    "keywords": [
      "common mistakes in probiotics gut health tips",
      "tips-probiotics-gut-health",
      "Common Mistakes in Probiotics Gut Health Tips guide",
      "best Common Mistakes in Probiotics Gut Health Tips",
      "Common Mistakes in Probiotics Gut Health Tips tips",
      "Common Mistakes in Probiotics Gut Health Tips 2026",
      "how to common mistakes in probiotics gut health tips"
    ],
    "title_tag": "Common Mistakes in Probiotics Gut Health Tips 101: Complete Beginner's Guide | probiotics-gut-health",
    "meta_description": "Take your knowledge of Common Mistakes in Probiotics Gut Health Tips to the next level with our detailed guide. Comprehensive coverage of all essential aspects.",
    "og_title": "Common Mistakes in Probiotics Gut Health Tips 101: Complete Beginner's Guide",
    "og_description": "Take your knowledge of Common Mistakes in Probiotics Gut Health Tips to the next level with our detailed guide. Comprehensive coverage of all essential aspects.",
    "og_type": "article",
    "twitter_card": "summary_large_image",
    "canonical_url": "/common-mistakes-in-probiotics-gut-health-tips-101-complete-beginners-guide",
    "robots": "index, follow"
  },
  "geo": {
    "country": "Australia",
    "city": "Brisbane",
    "language": "en",
    "target_regions": [
      "North America",
      "Europe",
      "Asia Pacific"
    ]
  },
  "image": {
    "id": "b724600489f26814dbb22143cf8d7588950b77e04ec84b0c31a0c518a09c8ca9",
    "url": "https://picsum.photos/914/594?random=454",
    "alt": "Featured image for: Common Mistakes in Probiotics Gut Health Tips 101: Complete Beginner's Guide",
    "width": 914,
    "height": 594
  }
}